{"openapi":"3.1.0","info":{"title":"MiniMarket Plus API","description":"API REST del backend MiniMarket Plus: productos, inventario, ventas, carrito y usuarios con roles CLIENTE, EMPLEADO y GERENTE. Autenticación JWT vía POST /api/auth/login. Respuestas HAL con HATEOAS (_links, _embedded) y paginación en listados.","contact":{"name":"Grupo 19","email":"minimarket@example.com"},"version":"1.1.0"},"servers":[{"url":"http://localhost","description":"Generated server url"}],"security":[{"bearerAuth":[]}],"tags":[{"name":"Pedidos","description":"Pedidos en línea para retiro o despacho"},{"name":"Reportes","description":"Reportes de gestión MiniMarket Plus"},{"name":"Sucursales","description":"Gestión de sucursales MiniMarket Plus"},{"name":"Detalle de ventas","description":"Líneas de detalle asociadas a ventas"},{"name":"Autenticación","description":"Login, registro, refresh token, logout y MFA"},{"name":"Productos","description":"Catálogo y gestión de productos del minimarket"},{"name":"Ventas","description":"Registro y consulta de ventas del minimarket"},{"name":"Administración","description":"Tareas administrativas del sistema"},{"name":"Carrito","description":"Carrito de compras por usuario autenticado"},{"name":"Público","description":"Endpoints públicos de verificación"},{"name":"Stock Sucursal","description":"Stock por sucursal y disponibilidad de productos"},{"name":"Categorías","description":"Clasificación de productos del catálogo"},{"name":"Inventario","description":"Movimientos de stock (entrada/salida). Roles EMPLEADO y GERENTE"},{"name":"Auditoría","description":"Consulta de logs de auditoría. Solo GERENTE"},{"name":"Promociones","description":"Ofertas y promociones centralizadas"},{"name":"Órdenes de Compra","description":"Reposición automática y recepción de mercadería"},{"name":"Usuarios","description":"Administración de usuarios. Solo rol GERENTE"}],"paths":{"/api/usuarios/{id}":{"get":{"tags":["Usuarios"],"summary":"Obtener usuario por ID","description":"Respuesta HAL con _links (self, usuarios).","operationId":"obtenerUsuarioPorId","parameters":[{"name":"id","in":"path","description":"ID del usuario","required":true,"schema":{"type":"integer","format":"int64"},"example":1}],"responses":{"200":{"description":"Usuario encontrado","content":{"*/*":{"schema":{"$ref":"#/components/schemas/EntityModelUsuarioResponseDTO"}}}},"401":{"description":"No autenticado"},"403":{"description":"Sin permisos (requiere GERENTE)"},"404":{"description":"Usuario no encontrado"}}},"put":{"tags":["Usuarios"],"summary":"Actualizar usuario","description":"Respuesta HAL con _links.","operationId":"actualizarUsuario","parameters":[{"name":"id","in":"path","description":"ID del usuario","required":true,"schema":{"type":"integer","format":"int64"},"example":1}],"requestBody":{"description":"Datos actualizados del usuario","content":{"application/json":{"schema":{"$ref":"#/components/schemas/UsuarioRequestDTO"},"examples":{"Actualizar dirección":{"description":"Actualizar dirección","value":{"username":"cliente1","nombre":"Cliente","apellido":"Demo","email":"cliente1@minimarket.cl","direccion":"Av. Principal 456","roleNames":["CLIENTE"]}}}}},"required":true},"responses":{"200":{"description":"Usuario actualizado","content":{"*/*":{"schema":{"$ref":"#/components/schemas/EntityModelUsuarioResponseDTO"}}}},"400":{"description":"Datos inválidos"},"401":{"description":"No autenticado"},"403":{"description":"Sin permisos (requiere GERENTE)"},"404":{"description":"Usuario no encontrado"}}},"delete":{"tags":["Usuarios"],"summary":"Eliminar usuario","operationId":"eliminarUsuario","parameters":[{"name":"id","in":"path","description":"ID del usuario","required":true,"schema":{"type":"integer","format":"int64"},"example":1}],"responses":{"204":{"description":"Usuario eliminado"},"401":{"description":"No autenticado"},"403":{"description":"Sin permisos (requiere GERENTE)"},"404":{"description":"Usuario no encontrado"}}}},"/api/sucursales/{id}":{"get":{"tags":["Sucursales"],"summary":"Obtener sucursal por ID","operationId":"obtenerSucursalPorId","parameters":[{"name":"id","in":"path","description":"ID de la sucursal","required":true,"schema":{"type":"integer","format":"int64"},"example":1}],"responses":{"200":{"description":"Sucursal encontrada","content":{"*/*":{"schema":{"$ref":"#/components/schemas/EntityModelSucursalResponseDTO"}}}},"404":{"description":"Sucursal no encontrada"}},"security":[]},"put":{"tags":["Sucursales"],"summary":"Actualizar sucursal","description":"Solo rol GERENTE. Respuesta HAL.","operationId":"actualizarSucursal","parameters":[{"name":"id","in":"path","required":true,"schema":{"type":"integer","format":"int64"}}],"requestBody":{"description":"Datos actualizados de la sucursal","content":{"application/json":{"schema":{"$ref":"#/components/schemas/SucursalRequestDTO"},"examples":{"Actualizar dirección":{"description":"Actualizar dirección","value":{"nombre":"MiniMarket Plus Providencia","direccion":"Av. Providencia 2120","comuna":"Providencia","activa":true}}}}},"required":true},"responses":{"200":{"description":"Sucursal actualizada","content":{"*/*":{"schema":{"$ref":"#/components/schemas/EntityModelSucursalResponseDTO"}}}},"404":{"description":"Sucursal no encontrada"}}},"delete":{"tags":["Sucursales"],"summary":"Eliminar sucursal","description":"Solo rol GERENTE","operationId":"eliminarSucursal","parameters":[{"name":"id","in":"path","required":true,"schema":{"type":"integer","format":"int64"}}],"responses":{"200":{"description":"OK"}}}},"/api/stock-sucursal/{id}":{"get":{"tags":["Stock Sucursal"],"summary":"Obtener stock por ID","operationId":"obtenerStockPorId","parameters":[{"name":"id","in":"path","required":true,"schema":{"type":"integer","format":"int64"}}],"responses":{"200":{"description":"OK","content":{"*/*":{"schema":{"$ref":"#/components/schemas/EntityModelStockSucursalResponseDTO"}}}}}},"put":{"tags":["Stock Sucursal"],"summary":"Actualizar stock","description":"Roles EMPLEADO y GERENTE. Respuesta HAL.","operationId":"actualizarStock","parameters":[{"name":"id","in":"path","required":true,"schema":{"type":"integer","format":"int64"}}],"requestBody":{"description":"Datos actualizados de stock","content":{"application/json":{"schema":{"$ref":"#/components/schemas/StockSucursalRequestDTO"},"examples":{"Reponer stock":{"description":"Reponer stock","value":{"producto":{"id":1},"sucursal":{"id":1},"cantidad":55,"stockMinimo":10}}}}},"required":true},"responses":{"200":{"description":"Stock actualizado","content":{"*/*":{"schema":{"$ref":"#/components/schemas/EntityModelStockSucursalResponseDTO"}}}},"400":{"description":"Datos inválidos"},"404":{"description":"Registro no encontrado"}}},"delete":{"tags":["Stock Sucursal"],"summary":"Eliminar registro de stock","description":"Solo rol GERENTE","operationId":"eliminarStock","parameters":[{"name":"id","in":"path","required":true,"schema":{"type":"integer","format":"int64"}}],"responses":{"200":{"description":"OK"}}}},"/api/promociones/{id}":{"get":{"tags":["Promociones"],"summary":"Obtener promoción por ID","operationId":"obtenerPromocionPorId","parameters":[{"name":"id","in":"path","description":"ID de la promoción","required":true,"schema":{"type":"integer","format":"int64"},"example":1}],"responses":{"200":{"description":"OK","content":{"*/*":{"schema":{"$ref":"#/components/schemas/EntityModelPromocionResponseDTO"}}}}},"security":[]},"put":{"tags":["Promociones"],"summary":"Actualizar promoción","description":"Solo rol GERENTE","operationId":"actualizarPromocion","parameters":[{"name":"id","in":"path","required":true,"schema":{"type":"integer","format":"int64"}}],"requestBody":{"content":{"application/json":{"schema":{"$ref":"#/components/schemas/PromocionRequestDTO"}}},"required":true},"responses":{"200":{"description":"OK","content":{"*/*":{"schema":{"$ref":"#/components/schemas/EntityModelPromocionResponseDTO"}}}}}},"delete":{"tags":["Promociones"],"summary":"Eliminar promoción","description":"Solo rol GERENTE","operationId":"eliminarPromocion","parameters":[{"name":"id","in":"path","required":true,"schema":{"type":"integer","format":"int64"}}],"responses":{"200":{"description":"OK"}}}},"/api/productos/{id}":{"get":{"tags":["Productos"],"summary":"Obtener producto por ID","description":"Respuesta HAL con _links (self, productos, categoria).","operationId":"obtenerProductoPorId","parameters":[{"name":"id","in":"path","description":"ID del producto","required":true,"schema":{"type":"integer","format":"int64"},"example":1}],"responses":{"200":{"description":"Producto encontrado","content":{"*/*":{"schema":{"$ref":"#/components/schemas/EntityModelProductoResponseDTO"}}}},"404":{"description":"Producto no encontrado"}},"security":[]},"put":{"tags":["Productos"],"summary":"Actualizar producto","description":"Solo rol GERENTE. Respuesta HAL con _links.","operationId":"actualizarProducto","parameters":[{"name":"id","in":"path","description":"ID del producto","required":true,"schema":{"type":"integer","format":"int64"},"example":1}],"requestBody":{"description":"Datos actualizados del producto","content":{"application/json":{"schema":{"$ref":"#/components/schemas/ProductoRequestDTO"},"examples":{"Actualizar stock":{"description":"Actualizar stock","value":{"nombre":"Arroz grano largo 1kg","precio":1890,"stock":15,"descripcion":"Stock actualizado","categoria":{"id":1}}}}}},"required":true},"responses":{"200":{"description":"Producto actualizado","content":{"*/*":{"schema":{"$ref":"#/components/schemas/EntityModelProductoResponseDTO"}}}},"400":{"description":"Datos inválidos"},"401":{"description":"No autenticado"},"403":{"description":"Sin permisos (requiere GERENTE)"},"404":{"description":"Producto no encontrado"}}},"delete":{"tags":["Productos"],"summary":"Eliminar producto","description":"Solo rol GERENTE","operationId":"eliminarProducto","parameters":[{"name":"id","in":"path","description":"ID del producto","required":true,"schema":{"type":"integer","format":"int64"},"example":1}],"responses":{"204":{"description":"Producto eliminado"},"401":{"description":"No autenticado"},"403":{"description":"Sin permisos (requiere GERENTE)"},"404":{"description":"Producto no encontrado"}}}},"/api/inventario/{id}":{"get":{"tags":["Inventario"],"summary":"Obtener movimiento por ID","description":"Respuesta HAL con _links (self, inventario, producto).","operationId":"obtenerMovimientoPorId","parameters":[{"name":"id","in":"path","description":"ID del movimiento","required":true,"schema":{"type":"integer","format":"int64"},"example":1}],"responses":{"200":{"description":"Movimiento encontrado","content":{"*/*":{"schema":{"$ref":"#/components/schemas/EntityModelInventarioResponseDTO"}}}},"401":{"description":"No autenticado"},"403":{"description":"Sin permisos"},"404":{"description":"Movimiento no encontrado"}}},"put":{"tags":["Inventario"],"summary":"Actualizar movimiento de inventario","description":"Respuesta HAL con _links.","operationId":"actualizarMovimiento","parameters":[{"name":"id","in":"path","description":"ID del movimiento","required":true,"schema":{"type":"integer","format":"int64"},"example":1}],"requestBody":{"description":"Datos actualizados del movimiento","content":{"application/json":{"schema":{"$ref":"#/components/schemas/InventarioRequestDTO"},"examples":{"Actualizar cantidad":{"description":"Actualizar cantidad","value":{"producto":{"id":1},"cantidad":5,"tipoMovimiento":"Salida"}}}}},"required":true},"responses":{"200":{"description":"Movimiento actualizado","content":{"*/*":{"schema":{"$ref":"#/components/schemas/EntityModelInventarioResponseDTO"}}}},"400":{"description":"Datos inválidos"},"401":{"description":"No autenticado"},"403":{"description":"Sin permisos"},"404":{"description":"Movimiento no encontrado"}}},"delete":{"tags":["Inventario"],"summary":"Eliminar movimiento","description":"Solo rol GERENTE","operationId":"eliminarMovimiento","parameters":[{"name":"id","in":"path","description":"ID del movimiento","required":true,"schema":{"type":"integer","format":"int64"},"example":1}],"responses":{"204":{"description":"Movimiento eliminado"},"401":{"description":"No autenticado"},"403":{"description":"Sin permisos (requiere GERENTE)"},"404":{"description":"Movimiento no encontrado"}}}},"/api/detalle-ventas/{id}":{"get":{"tags":["Detalle de ventas"],"summary":"Obtener detalle de venta por ID","operationId":"obtenerDetalleVentaPorId","parameters":[{"name":"id","in":"path","description":"ID del detalle","required":true,"schema":{"type":"integer","format":"int64"},"example":1}],"responses":{"200":{"description":"Detalle encontrado","content":{"*/*":{"schema":{"$ref":"#/components/schemas/DetalleVentaResponseDTO"}}}},"401":{"description":"No autenticado"},"403":{"description":"Sin permisos"},"404":{"description":"Detalle no encontrado"}}},"put":{"tags":["Detalle de ventas"],"summary":"Actualizar detalle de venta","operationId":"actualizarDetalleVenta","parameters":[{"name":"id","in":"path","description":"ID del detalle","required":true,"schema":{"type":"integer","format":"int64"},"example":1}],"requestBody":{"content":{"application/json":{"schema":{"$ref":"#/components/schemas/DetalleVentaRequestDTO"}}},"required":true},"responses":{"200":{"description":"Detalle actualizado","content":{"*/*":{"schema":{"$ref":"#/components/schemas/DetalleVentaResponseDTO"}}}},"400":{"description":"Datos inválidos"},"401":{"description":"No autenticado"},"403":{"description":"Sin permisos (requiere EMPLEADO o GERENTE)"},"404":{"description":"Detalle no encontrado"}}},"delete":{"tags":["Detalle de ventas"],"summary":"Eliminar detalle de venta","operationId":"eliminarDetalleVenta","parameters":[{"name":"id","in":"path","description":"ID del detalle","required":true,"schema":{"type":"integer","format":"int64"},"example":1}],"responses":{"204":{"description":"Detalle eliminado"},"401":{"description":"No autenticado"},"403":{"description":"Sin permisos (requiere EMPLEADO o GERENTE)"},"404":{"description":"Detalle no encontrado"}}}},"/api/categorias/{id}":{"get":{"tags":["Categorías"],"summary":"Obtener categoría por ID","operationId":"obtenerCategoriaPorId","parameters":[{"name":"id","in":"path","description":"ID de la categoría","required":true,"schema":{"type":"integer","format":"int64"},"example":1}],"responses":{"200":{"description":"Categoría encontrada","content":{"*/*":{"schema":{"$ref":"#/components/schemas/EntityModelCategoriaResponseDTO"}}}},"404":{"description":"Categoría no encontrada"}},"security":[]},"put":{"tags":["Categorías"],"summary":"Actualizar categoría","description":"Solo rol GERENTE","operationId":"actualizarCategoria","parameters":[{"name":"id","in":"path","description":"ID de la categoría","required":true,"schema":{"type":"integer","format":"int64"},"example":1}],"requestBody":{"content":{"application/json":{"schema":{"$ref":"#/components/schemas/CategoriaRequestDTO"}}},"required":true},"responses":{"200":{"description":"Categoría actualizada","content":{"*/*":{"schema":{"$ref":"#/components/schemas/EntityModelCategoriaResponseDTO"}}}},"400":{"description":"Datos inválidos"},"401":{"description":"No autenticado"},"403":{"description":"Sin permisos (requiere GERENTE)"},"404":{"description":"Categoría no encontrada"}}},"delete":{"tags":["Categorías"],"summary":"Eliminar categoría","description":"Solo rol GERENTE","operationId":"eliminarCategoria","parameters":[{"name":"id","in":"path","description":"ID de la categoría","required":true,"schema":{"type":"integer","format":"int64"},"example":1}],"responses":{"204":{"description":"Categoría eliminada"},"401":{"description":"No autenticado"},"403":{"description":"Sin permisos (requiere GERENTE)"},"404":{"description":"Categoría no encontrada"}}}},"/api/carrito/{id}":{"get":{"tags":["Carrito"],"summary":"Obtener item del carrito por ID","description":"Respuesta HAL con _links (self, carrito, usuario, producto).","operationId":"obtenerCarritoPorId","parameters":[{"name":"id","in":"path","description":"ID del item en carrito","required":true,"schema":{"type":"integer","format":"int64"},"example":1}],"responses":{"200":{"description":"Item encontrado","content":{"*/*":{"schema":{"$ref":"#/components/schemas/EntityModelCarritoResponseDTO"}}}},"401":{"description":"No autenticado"},"403":{"description":"Sin permisos"},"404":{"description":"Item no encontrado"}}},"put":{"tags":["Carrito"],"summary":"Actualizar item del carrito","description":"Respuesta HAL con _links.","operationId":"actualizarCarrito","parameters":[{"name":"id","in":"path","description":"ID del item en carrito","required":true,"schema":{"type":"integer","format":"int64"},"example":1}],"requestBody":{"description":"Datos actualizados del item","content":{"application/json":{"schema":{"$ref":"#/components/schemas/CarritoRequestDTO"},"examples":{"Actualizar cantidad":{"description":"Actualizar cantidad","value":{"usuario":{"id":1},"producto":{"id":1},"cantidad":3}}}}},"required":true},"responses":{"200":{"description":"Item actualizado","content":{"*/*":{"schema":{"$ref":"#/components/schemas/EntityModelCarritoResponseDTO"}}}},"400":{"description":"Datos inválidos"},"401":{"description":"No autenticado"},"403":{"description":"Sin permisos"},"404":{"description":"Item no encontrado"}}},"delete":{"tags":["Carrito"],"summary":"Eliminar producto del carrito","operationId":"eliminarProductoDelCarrito","parameters":[{"name":"id","in":"path","description":"ID del item en carrito","required":true,"schema":{"type":"integer","format":"int64"},"example":1}],"responses":{"204":{"description":"Item eliminado"},"401":{"description":"No autenticado"},"403":{"description":"Sin permisos"},"404":{"description":"Item no encontrado"}}}},"/api/ventas":{"get":{"tags":["Ventas"],"summary":"Listar ventas","description":"Paginado con HATEOAS","operationId":"listarVentas","parameters":[{"name":"page","in":"query","description":"Zero-based page index (0..N)","required":false,"schema":{"type":"integer","default":0,"minimum":0}},{"name":"size","in":"query","description":"The size of the page to be returned","required":false,"schema":{"type":"integer","default":10,"minimum":1}},{"name":"sort","in":"query","description":"Sorting criteria in the format: property,(asc|desc). Default sort order is ascending. Multiple sort criteria are supported.","required":false,"schema":{"type":"array","items":{"type":"string"}}},{"name":"pagedAssembler","in":"query","required":true,"schema":{"$ref":"#/components/schemas/PagedResourcesAssemblerVentaResponseDTO"}}],"responses":{"200":{"description":"Página de ventas","content":{"*/*":{"schema":{"$ref":"#/components/schemas/PagedModelEntityModelVentaResponseDTO"}}}},"401":{"description":"No autenticado"},"403":{"description":"Sin permisos"}}},"post":{"tags":["Ventas"],"summary":"Guardar venta (CRUD directo)","operationId":"guardarVenta","requestBody":{"content":{"application/json":{"schema":{"$ref":"#/components/schemas/VentaRequestDTO"}}},"required":true},"responses":{"200":{"description":"Venta guardada","content":{"*/*":{"schema":{"$ref":"#/components/schemas/EntityModelVentaResponseDTO"}}}},"400":{"description":"Datos inválidos"},"401":{"description":"No autenticado"},"403":{"description":"Sin permisos"}}}},"/api/ventas/registrar":{"post":{"tags":["Ventas"],"summary":"Registrar venta con items","description":"Descuenta stock y calcula total. Roles EMPLEADO y GERENTE","operationId":"registrarVenta","requestBody":{"content":{"application/json":{"schema":{"$ref":"#/components/schemas/VentaRegistroDTO"}}},"required":true},"responses":{"200":{"description":"Venta registrada","content":{"*/*":{"schema":{"$ref":"#/components/schemas/EntityModelVentaResponseDTO"}}}},"400":{"description":"Datos inválidos o stock insuficiente"},"401":{"description":"No autenticado"},"403":{"description":"Sin permisos (requiere EMPLEADO o GERENTE)"}}}},"/api/usuarios":{"get":{"tags":["Usuarios"],"summary":"Listar usuarios","description":"Lista paginada HAL con _embedded, page y links de paginación.","operationId":"listarUsuarios","parameters":[{"name":"page","in":"query","description":"Zero-based page index (0..N)","required":false,"schema":{"type":"integer","default":0,"minimum":0}},{"name":"size","in":"query","description":"The size of the page to be returned","required":false,"schema":{"type":"integer","default":10,"minimum":1}},{"name":"sort","in":"query","description":"Sorting criteria in the format: property,(asc|desc). Default sort order is ascending. Multiple sort criteria are supported.","required":false,"schema":{"type":"array","items":{"type":"string"}}},{"name":"pagedAssembler","in":"query","required":true,"schema":{"$ref":"#/components/schemas/PagedResourcesAssemblerUsuarioResponseDTO"}}],"responses":{"200":{"description":"Página de usuarios","content":{"*/*":{"schema":{"$ref":"#/components/schemas/PagedModelEntityModelUsuarioResponseDTO"}}}},"401":{"description":"No autenticado"},"403":{"description":"Sin permisos (requiere GERENTE)"}}},"post":{"tags":["Usuarios"],"summary":"Crear usuario","description":"Respuesta HAL con _links.","operationId":"guardarUsuario","requestBody":{"description":"Usuario a crear","content":{"application/json":{"schema":{"$ref":"#/components/schemas/UsuarioRequestDTO"},"examples":{"Usuario cliente":{"description":"Usuario cliente","value":{"username":"cliente_nuevo","password":"cliente123","nombre":"Ana","apellido":"Pérez","email":"ana@example.com","direccion":"Calle 123","roleNames":["CLIENTE"]}}}}},"required":true},"responses":{"200":{"description":"Usuario creado","content":{"*/*":{"schema":{"$ref":"#/components/schemas/EntityModelUsuarioResponseDTO"}}}},"400":{"description":"Datos inválidos"},"401":{"description":"No autenticado"},"403":{"description":"Sin permisos (requiere GERENTE)"}}}},"/api/sucursales":{"get":{"tags":["Sucursales"],"summary":"Listar sucursales","description":"Consulta pública paginada con HATEOAS","operationId":"listarSucursales","parameters":[{"name":"page","in":"query","description":"Zero-based page index (0..N)","required":false,"schema":{"type":"integer","default":0,"minimum":0}},{"name":"size","in":"query","description":"The size of the page to be returned","required":false,"schema":{"type":"integer","default":10,"minimum":1}},{"name":"sort","in":"query","description":"Sorting criteria in the format: property,(asc|desc). Default sort order is ascending. Multiple sort criteria are supported.","required":false,"schema":{"type":"array","items":{"type":"string"}}},{"name":"pagedAssembler","in":"query","required":true,"schema":{"$ref":"#/components/schemas/PagedResourcesAssemblerSucursalResponseDTO"}}],"responses":{"200":{"description":"Página de sucursales","content":{"*/*":{"schema":{"$ref":"#/components/schemas/PagedModelEntityModelSucursalResponseDTO"}}}}},"security":[]},"post":{"tags":["Sucursales"],"summary":"Crear sucursal","description":"Solo rol GERENTE. Respuesta HAL con _links.","operationId":"guardarSucursal","requestBody":{"description":"Sucursal a crear","content":{"application/json":{"schema":{"$ref":"#/components/schemas/SucursalRequestDTO"},"examples":{"Sucursal Providencia":{"description":"Sucursal Providencia","value":{"nombre":"MiniMarket Plus Las Condes","direccion":"Av. Apoquindo 4500","comuna":"Las Condes","activa":true}}}}},"required":true},"responses":{"200":{"description":"Sucursal creada","content":{"*/*":{"schema":{"$ref":"#/components/schemas/EntityModelSucursalResponseDTO"}}}},"400":{"description":"Datos inválidos"},"403":{"description":"Sin permisos (requiere GERENTE)"}}}},"/api/stock-sucursal":{"get":{"tags":["Stock Sucursal"],"summary":"Listar stock por sucursal","description":"Paginado con HATEOAS. Roles EMPLEADO y GERENTE","operationId":"listarStockSucursal","parameters":[{"name":"page","in":"query","description":"Zero-based page index (0..N)","required":false,"schema":{"type":"integer","default":0,"minimum":0}},{"name":"size","in":"query","description":"The size of the page to be returned","required":false,"schema":{"type":"integer","default":10,"minimum":1}},{"name":"sort","in":"query","description":"Sorting criteria in the format: property,(asc|desc). Default sort order is ascending. Multiple sort criteria are supported.","required":false,"schema":{"type":"array","items":{"type":"string"}}},{"name":"pagedAssembler","in":"query","required":true,"schema":{"$ref":"#/components/schemas/PagedResourcesAssemblerStockSucursalResponseDTO"}}],"responses":{"200":{"description":"OK","content":{"*/*":{"schema":{"$ref":"#/components/schemas/PagedModelEntityModelStockSucursalResponseDTO"}}}}}},"post":{"tags":["Stock Sucursal"],"summary":"Crear registro de stock","description":"Roles EMPLEADO y GERENTE. Respuesta HAL con _links.","operationId":"guardarStock","requestBody":{"description":"Stock por sucursal a crear","content":{"application/json":{"schema":{"$ref":"#/components/schemas/StockSucursalRequestDTO"},"examples":{"Stock Providencia":{"description":"Stock Providencia","value":{"producto":{"id":1},"sucursal":{"id":1},"cantidad":40,"stockMinimo":10}}}}},"required":true},"responses":{"200":{"description":"Stock creado (HAL)","content":{"*/*":{"schema":{"$ref":"#/components/schemas/EntityModelStockSucursalResponseDTO"}}}},"400":{"description":"Datos inválidos"},"403":{"description":"Sin permisos"}}}},"/api/promociones":{"get":{"tags":["Promociones"],"summary":"Listar promociones","description":"Consulta pública paginada con HATEOAS","operationId":"listarPromociones","parameters":[{"name":"page","in":"query","description":"Zero-based page index (0..N)","required":false,"schema":{"type":"integer","default":0,"minimum":0}},{"name":"size","in":"query","description":"The size of the page to be returned","required":false,"schema":{"type":"integer","default":10,"minimum":1}},{"name":"sort","in":"query","description":"Sorting criteria in the format: property,(asc|desc). Default sort order is ascending. Multiple sort criteria are supported.","required":false,"schema":{"type":"array","items":{"type":"string"}}},{"name":"pagedAssembler","in":"query","required":true,"schema":{"$ref":"#/components/schemas/PagedResourcesAssemblerPromocionResponseDTO"}}],"responses":{"200":{"description":"OK","content":{"*/*":{"schema":{"$ref":"#/components/schemas/PagedModelEntityModelPromocionResponseDTO"}}}}},"security":[]},"post":{"tags":["Promociones"],"summary":"Crear promoción","description":"Solo rol GERENTE. Respuesta HAL con _links.","operationId":"guardarPromocion","requestBody":{"description":"Promoción centralizada","content":{"application/json":{"schema":{"$ref":"#/components/schemas/PromocionRequestDTO"},"examples":{"Promo 15% producto en sucursal":{"description":"Promo 15% producto en sucursal","value":{"nombre":"Promo EFT S9","descripcion":"Descuento de evidencia","descuentoPorcentaje":15,"fechaInicio":"2026-01-01T00:00:00.000Z","fechaFin":"2026-12-31T23:59:59.000Z","activa":true,"producto":{"id":1},"sucursal":{"id":1}}}}}},"required":true},"responses":{"200":{"description":"Promoción creada","content":{"*/*":{"schema":{"$ref":"#/components/schemas/EntityModelPromocionResponseDTO"}}}},"400":{"description":"Datos inválidos"},"403":{"description":"Sin permisos (requiere GERENTE)"}}}},"/api/productos":{"get":{"tags":["Productos"],"summary":"Listar productos","description":"Consulta pública paginada del catálogo. Respuesta HAL con _embedded, page y links de paginación.","operationId":"listarProductos","parameters":[{"name":"page","in":"query","description":"Zero-based page index (0..N)","required":false,"schema":{"type":"integer","default":0,"minimum":0}},{"name":"size","in":"query","description":"The size of the page to be returned","required":false,"schema":{"type":"integer","default":10,"minimum":1}},{"name":"sort","in":"query","description":"Sorting criteria in the format: property,(asc|desc). Default sort order is ascending. Multiple sort criteria are supported.","required":false,"schema":{"type":"array","items":{"type":"string"}}},{"name":"pagedAssembler","in":"query","required":true,"schema":{"$ref":"#/components/schemas/PagedResourcesAssemblerProductoResponseDTO"}}],"responses":{"200":{"description":"Página de productos con HATEOAS","content":{"*/*":{"schema":{"$ref":"#/components/schemas/ProductoResponseDTO"}}}}},"security":[]},"post":{"tags":["Productos"],"summary":"Crear producto","description":"Solo rol GERENTE. Respuesta HAL con _links.","operationId":"guardarProducto","requestBody":{"description":"Producto a crear","content":{"application/json":{"schema":{"$ref":"#/components/schemas/ProductoRequestDTO"},"examples":{"Producto demo":{"description":"Producto demo","value":{"nombre":"Galletas surtidas 200g","precio":990,"stock":25,"descripcion":"Snack dulce","categoria":{"id":1}}}}}},"required":true},"responses":{"200":{"description":"Producto creado","content":{"*/*":{"schema":{"$ref":"#/components/schemas/EntityModelProductoResponseDTO"}}}},"400":{"description":"Datos inválidos"},"401":{"description":"No autenticado"},"403":{"description":"Sin permisos (requiere GERENTE)"}}}},"/api/pedidos/registrar":{"post":{"tags":["Pedidos"],"summary":"Registrar pedido","description":"Usuario autenticado. Descuenta stock de sucursal, aplica promociones y responde HAL con _links.","operationId":"registrarPedido","requestBody":{"description":"Pedido RETIRO o DESPACHO","content":{"application/json":{"schema":{"$ref":"#/components/schemas/PedidoRegistroDTO"},"examples":{"Retiro en tienda":{"description":"Retiro en tienda","value":{"usuarioId":1,"sucursalId":1,"tipoEntrega":"RETIRO","items":[{"productoId":1,"cantidad":2}]}},"Despacho a domicilio":{"description":"Despacho a domicilio","value":{"usuarioId":1,"sucursalId":1,"tipoEntrega":"DESPACHO","direccionEntrega":"Av. Providencia 1234, Santiago","items":[{"productoId":1,"cantidad":1}]}}}}},"required":true},"responses":{"200":{"description":"Pedido registrado (HAL)","content":{"*/*":{"schema":{"$ref":"#/components/schemas/EntityModelPedidoResponseDTO"}}}},"400":{"description":"Datos inválidos o stock insuficiente"},"401":{"description":"No autenticado"}}}},"/api/ordenes-compra/{id}/confirmar-recepcion":{"post":{"tags":["Órdenes de Compra"],"summary":"Confirmar recepción","description":"Incrementa stock en sucursal y marca orden como RECIBIDA. Respuesta HAL.","operationId":"confirmarRecepcion","parameters":[{"name":"id","in":"path","required":true,"schema":{"type":"integer","format":"int64"}}],"responses":{"200":{"description":"Recepción confirmada (HAL)","content":{"*/*":{"schema":{"$ref":"#/components/schemas/EntityModelOrdenCompraResponseDTO"}}}},"400":{"description":"Orden ya recibida"},"404":{"description":"Orden no encontrada"}}}},"/api/ordenes-compra/generar-automaticas":{"post":{"tags":["Órdenes de Compra"],"summary":"Generar órdenes automáticas","description":"Crea órdenes para productos con stock <= mínimo en cada sucursal. Cada ítem responde HAL con _links.","operationId":"generarOrdenesAutomaticas","responses":{"200":{"description":"Órdenes generadas (lista de EntityModel HAL)","content":{"*/*":{"schema":{"type":"array","items":{"$ref":"#/components/schemas/EntityModelOrdenCompraResponseDTO"}}}}}}}},"/api/inventario":{"get":{"tags":["Inventario"],"summary":"Listar movimientos de inventario","description":"Lista paginada HAL con _embedded, page y links de paginación.","operationId":"listarMovimientosDeInventario","parameters":[{"name":"page","in":"query","description":"Zero-based page index (0..N)","required":false,"schema":{"type":"integer","default":0,"minimum":0}},{"name":"size","in":"query","description":"The size of the page to be returned","required":false,"schema":{"type":"integer","default":10,"minimum":1}},{"name":"sort","in":"query","description":"Sorting criteria in the format: property,(asc|desc). Default sort order is ascending. Multiple sort criteria are supported.","required":false,"schema":{"type":"array","items":{"type":"string"}}},{"name":"pagedAssembler","in":"query","required":true,"schema":{"$ref":"#/components/schemas/PagedResourcesAssemblerInventarioResponseDTO"}}],"responses":{"200":{"description":"Página de movimientos","content":{"*/*":{"schema":{"$ref":"#/components/schemas/PagedModelEntityModelInventarioResponseDTO"}}}},"401":{"description":"No autenticado"},"403":{"description":"Sin permisos (requiere EMPLEADO o GERENTE)"}}},"post":{"tags":["Inventario"],"summary":"Registrar movimiento de inventario","description":"Ejemplo: tipoMovimiento Entrada o Salida. Respuesta HAL con _links.","operationId":"registrarMovimiento","requestBody":{"description":"Movimiento de inventario a registrar","content":{"application/json":{"schema":{"$ref":"#/components/schemas/InventarioRequestDTO"},"examples":{"Entrada de stock":{"description":"Entrada de stock","value":{"producto":{"id":1},"cantidad":10,"tipoMovimiento":"Entrada"}}}}},"required":true},"responses":{"200":{"description":"Movimiento registrado","content":{"*/*":{"schema":{"$ref":"#/components/schemas/EntityModelInventarioResponseDTO"}}}},"400":{"description":"Datos inválidos"},"401":{"description":"No autenticado"},"403":{"description":"Sin permisos"}}}},"/api/detalle-ventas":{"get":{"tags":["Detalle de ventas"],"summary":"Listar detalles de venta","operationId":"listarDetalleVentas","responses":{"200":{"description":"Lista de detalles","content":{"*/*":{"schema":{"type":"array","items":{"$ref":"#/components/schemas/DetalleVentaResponseDTO"}}}}},"401":{"description":"No autenticado"},"403":{"description":"Sin permisos"}}},"post":{"tags":["Detalle de ventas"],"summary":"Crear detalle de venta","operationId":"guardarDetalleVenta","requestBody":{"content":{"application/json":{"schema":{"$ref":"#/components/schemas/DetalleVentaRequestDTO"}}},"required":true},"responses":{"200":{"description":"Detalle creado","content":{"*/*":{"schema":{"$ref":"#/components/schemas/DetalleVentaResponseDTO"}}}},"400":{"description":"Datos inválidos"},"401":{"description":"No autenticado"},"403":{"description":"Sin permisos"}}}},"/api/categorias":{"get":{"tags":["Categorías"],"summary":"Listar categorías","description":"Consulta pública paginada con HATEOAS","operationId":"listarCategorias","parameters":[{"name":"page","in":"query","description":"Zero-based page index (0..N)","required":false,"schema":{"type":"integer","default":0,"minimum":0}},{"name":"size","in":"query","description":"The size of the page to be returned","required":false,"schema":{"type":"integer","default":10,"minimum":1}},{"name":"sort","in":"query","description":"Sorting criteria in the format: property,(asc|desc). Default sort order is ascending. Multiple sort criteria are supported.","required":false,"schema":{"type":"array","items":{"type":"string"}}},{"name":"pagedAssembler","in":"query","required":true,"schema":{"$ref":"#/components/schemas/PagedResourcesAssemblerCategoriaResponseDTO"}}],"responses":{"200":{"description":"Página de categorías","content":{"*/*":{"schema":{"$ref":"#/components/schemas/PagedModelEntityModelCategoriaResponseDTO"}}}}},"security":[]},"post":{"tags":["Categorías"],"summary":"Crear categoría","description":"Solo rol GERENTE","operationId":"guardarCategoria","requestBody":{"content":{"application/json":{"schema":{"$ref":"#/components/schemas/CategoriaRequestDTO"}}},"required":true},"responses":{"200":{"description":"Categoría creada","content":{"*/*":{"schema":{"$ref":"#/components/schemas/EntityModelCategoriaResponseDTO"}}}},"400":{"description":"Datos inválidos"},"401":{"description":"No autenticado"},"403":{"description":"Sin permisos (requiere GERENTE)"}}}},"/api/carrito":{"get":{"tags":["Carrito"],"summary":"Listar items del carrito","description":"Lista paginada HAL con _embedded, page y links de paginación.","operationId":"listarCarrito","parameters":[{"name":"page","in":"query","description":"Zero-based page index (0..N)","required":false,"schema":{"type":"integer","default":0,"minimum":0}},{"name":"size","in":"query","description":"The size of the page to be returned","required":false,"schema":{"type":"integer","default":10,"minimum":1}},{"name":"sort","in":"query","description":"Sorting criteria in the format: property,(asc|desc). Default sort order is ascending. Multiple sort criteria are supported.","required":false,"schema":{"type":"array","items":{"type":"string"}}},{"name":"pagedAssembler","in":"query","required":true,"schema":{"$ref":"#/components/schemas/PagedResourcesAssemblerCarritoResponseDTO"}}],"responses":{"200":{"description":"Página de items del carrito","content":{"*/*":{"schema":{"$ref":"#/components/schemas/PagedModelEntityModelCarritoResponseDTO"}}}},"401":{"description":"No autenticado"},"403":{"description":"Sin permisos"}}},"post":{"tags":["Carrito"],"summary":"Agregar producto al carrito","description":"Respuesta HAL con _links.","operationId":"agregarProductoAlCarrito","requestBody":{"description":"Producto y cantidad a agregar","content":{"application/json":{"schema":{"$ref":"#/components/schemas/CarritoRequestDTO"},"examples":{"Agregar al carrito":{"description":"Agregar al carrito","value":{"usuario":{"id":1},"producto":{"id":1},"cantidad":2}}}}},"required":true},"responses":{"200":{"description":"Producto agregado","content":{"*/*":{"schema":{"$ref":"#/components/schemas/EntityModelCarritoResponseDTO"}}}},"400":{"description":"Datos inválidos"},"401":{"description":"No autenticado"},"403":{"description":"Sin permisos"}}}},"/api/auth/register":{"post":{"tags":["Autenticación"],"summary":"Registrar nuevo usuario cliente","operationId":"register","requestBody":{"content":{"application/json":{"schema":{"$ref":"#/components/schemas/RegisterRequest"}}},"required":true},"responses":{"201":{"description":"Usuario registrado con tokens","content":{"*/*":{"schema":{"$ref":"#/components/schemas/TokenPairResponse"}}}},"400":{"description":"Datos inválidos"}},"security":[]}},"/api/auth/refresh":{"post":{"tags":["Autenticación"],"summary":"Renovar access token","operationId":"refresh","requestBody":{"content":{"application/json":{"schema":{"$ref":"#/components/schemas/RefreshTokenRequest"}}},"required":true},"responses":{"200":{"description":"Nuevo par de tokens","content":{"*/*":{"schema":{"$ref":"#/components/schemas/TokenPairResponse"}}}},"401":{"description":"Refresh token inválido o expirado"}},"security":[]}},"/api/auth/mfa/verify":{"post":{"tags":["Autenticación"],"summary":"Verificar código MFA y obtener tokens","operationId":"verifyMfa","requestBody":{"content":{"application/json":{"schema":{"$ref":"#/components/schemas/MfaVerifyRequest"}}},"required":true},"responses":{"200":{"description":"Tokens emitidos tras verificación MFA","content":{"*/*":{"schema":{"$ref":"#/components/schemas/TokenPairResponse"}}}},"401":{"description":"Token MFA o código TOTP inválido"}},"security":[]}},"/api/auth/mfa/setup":{"post":{"tags":["Autenticación"],"summary":"Configurar MFA TOTP","description":"Solo GERENTE autenticado","operationId":"setupMfa","responses":{"200":{"description":"QR y secreto para configurar MFA","content":{"*/*":{"schema":{"$ref":"#/components/schemas/MfaSetupResponse"}}}},"401":{"description":"No autenticado"},"403":{"description":"Sin permisos (requiere GERENTE)"}}}},"/api/auth/mfa/confirm":{"post":{"tags":["Autenticación"],"summary":"Confirmar activación MFA","operationId":"confirmMfa","requestBody":{"content":{"application/json":{"schema":{"$ref":"#/components/schemas/MfaConfirmRequest"}}},"required":true},"responses":{"200":{"description":"MFA activado","content":{"*/*":{"schema":{"$ref":"#/components/schemas/MapMessage"}}}},"401":{"description":"No autenticado"},"403":{"description":"Sin permisos (requiere GERENTE)"}}}},"/api/auth/logout":{"post":{"tags":["Autenticación"],"summary":"Cerrar sesión","operationId":"logout","requestBody":{"content":{"application/json":{"schema":{"$ref":"#/components/schemas/LogoutRequest"}}},"required":true},"responses":{"200":{"description":"Sesión cerrada","content":{"*/*":{"schema":{"$ref":"#/components/schemas/MapMessage"}}}},"401":{"description":"Refresh token inválido"}},"security":[]}},"/api/auth/login":{"post":{"tags":["Autenticación"],"summary":"Iniciar sesión","description":"Retorna accessToken y refreshToken. Usuarios demo: cliente1/cliente123, empleado1/empleado123, gerente1/gerente123","operationId":"login","requestBody":{"content":{"application/json":{"schema":{"$ref":"#/components/schemas/LoginRequest"},"example":{"username":"cliente1","password":"cliente123"}}},"required":true},"responses":{"200":{"description":"Login exitoso o desafío MFA","content":{"*/*":{"schema":{"$ref":"#/components/schemas/TokenPairResponse"}}}},"400":{"description":"Credenciales nulas o vacías"},"401":{"description":"Credenciales inválidas"},"429":{"description":"Cuenta bloqueada por intentos fallidos"}},"security":[]}},"/api/admin/retention/run":{"post":{"tags":["Administración"],"summary":"Ejecutar retención de datos","description":"Anonimiza usuarios inactivos según política configurada. Solo GERENTE","operationId":"runRetention","responses":{"200":{"description":"Proceso ejecutado","content":{"*/*":{"schema":{"type":"object","additionalProperties":{}}}}},"401":{"description":"No autenticado"},"403":{"description":"Sin permisos (requiere GERENTE)"}}}},"/api/pedidos/{id}/estado":{"patch":{"tags":["Pedidos"],"summary":"Actualizar estado del pedido","description":"Roles EMPLEADO y GERENTE. Respuesta HAL.","operationId":"actualizarEstado","parameters":[{"name":"id","in":"path","required":true,"schema":{"type":"integer","format":"int64"}}],"requestBody":{"description":"Nuevo estado del pedido","content":{"application/json":{"schema":{"$ref":"#/components/schemas/PedidoEstadoUpdateDTO"},"examples":{"Confirmar pedido":{"description":"Confirmar pedido","value":{"estado":"CONFIRMADO"}}}}},"required":true},"responses":{"200":{"description":"Estado actualizado","content":{"*/*":{"schema":{"$ref":"#/components/schemas/EntityModelPedidoResponseDTO"}}}},"404":{"description":"Pedido no encontrado"}}}},"/public/hola":{"get":{"tags":["Público"],"summary":"Saludo público","description":"Endpoint de prueba sin autenticación","operationId":"holaMundo","responses":{"200":{"description":"Mensaje de bienvenida","content":{"*/*":{"schema":{"type":"string"}}}}},"security":[]}},"/api/ventas/{id}":{"get":{"tags":["Ventas"],"summary":"Obtener venta por ID","operationId":"obtenerVentaPorId","parameters":[{"name":"id","in":"path","description":"ID de la venta","required":true,"schema":{"type":"integer","format":"int64"},"example":1}],"responses":{"200":{"description":"Venta encontrada","content":{"*/*":{"schema":{"$ref":"#/components/schemas/EntityModelVentaResponseDTO"}}}},"401":{"description":"No autenticado"},"403":{"description":"Sin permisos"},"404":{"description":"Venta no encontrada"}}}},"/api/stock-sucursal/disponibilidad/{sucursalId}":{"get":{"tags":["Stock Sucursal"],"summary":"Consultar disponibilidad por sucursal","description":"Consulta pública","operationId":"consultarDisponibilidad","parameters":[{"name":"sucursalId","in":"path","description":"ID de la sucursal","required":true,"schema":{"type":"integer","format":"int64"},"example":1}],"responses":{"200":{"description":"OK","content":{"*/*":{"schema":{"type":"array","items":{"$ref":"#/components/schemas/DisponibilidadResponseDTO"}}}}}},"security":[]}},"/api/reportes/rotacion-productos":{"get":{"tags":["Reportes"],"summary":"Rotación de productos","description":"Combina ventas y pedidos para identificar productos más y menos vendidos","operationId":"obtenerRotacionProductos","responses":{"200":{"description":"Reporte de rotación","content":{"*/*":{"schema":{"type":"array","items":{"$ref":"#/components/schemas/RotacionProductoResponseDTO"}}}}}}}},"/api/promociones/activas":{"get":{"tags":["Promociones"],"summary":"Listar promociones activas","description":"Consulta pública de promociones vigentes","operationId":"listarPromocionesActivas","responses":{"200":{"description":"OK","content":{"*/*":{"schema":{"type":"array","items":{"$ref":"#/components/schemas/PromocionResponseDTO"}}}}}},"security":[]}},"/api/pedidos":{"get":{"tags":["Pedidos"],"summary":"Listar pedidos","description":"Paginado con HATEOAS. Usuario autenticado","operationId":"listarPedidos","parameters":[{"name":"page","in":"query","description":"Zero-based page index (0..N)","required":false,"schema":{"type":"integer","default":0,"minimum":0}},{"name":"size","in":"query","description":"The size of the page to be returned","required":false,"schema":{"type":"integer","default":10,"minimum":1}},{"name":"sort","in":"query","description":"Sorting criteria in the format: property,(asc|desc). Default sort order is ascending. Multiple sort criteria are supported.","required":false,"schema":{"type":"array","items":{"type":"string"}}},{"name":"pagedAssembler","in":"query","required":true,"schema":{"$ref":"#/components/schemas/PagedResourcesAssemblerPedidoResponseDTO"}}],"responses":{"200":{"description":"OK","content":{"*/*":{"schema":{"$ref":"#/components/schemas/PagedModelEntityModelPedidoResponseDTO"}}}}}}},"/api/pedidos/{id}":{"get":{"tags":["Pedidos"],"summary":"Obtener pedido por ID","operationId":"obtenerPedidoPorId","parameters":[{"name":"id","in":"path","description":"ID del pedido","required":true,"schema":{"type":"integer","format":"int64"},"example":1}],"responses":{"200":{"description":"OK","content":{"*/*":{"schema":{"$ref":"#/components/schemas/EntityModelPedidoResponseDTO"}}}}}}},"/api/ordenes-compra":{"get":{"tags":["Órdenes de Compra"],"summary":"Listar órdenes de compra","description":"Paginado con HATEOAS","operationId":"listarOrdenesCompra","parameters":[{"name":"page","in":"query","description":"Zero-based page index (0..N)","required":false,"schema":{"type":"integer","default":0,"minimum":0}},{"name":"size","in":"query","description":"The size of the page to be returned","required":false,"schema":{"type":"integer","default":10,"minimum":1}},{"name":"sort","in":"query","description":"Sorting criteria in the format: property,(asc|desc). Default sort order is ascending. Multiple sort criteria are supported.","required":false,"schema":{"type":"array","items":{"type":"string"}}},{"name":"pagedAssembler","in":"query","required":true,"schema":{"$ref":"#/components/schemas/PagedResourcesAssemblerOrdenCompraResponseDTO"}}],"responses":{"200":{"description":"OK","content":{"*/*":{"schema":{"$ref":"#/components/schemas/PagedModelEntityModelOrdenCompraResponseDTO"}}}}}}},"/api/ordenes-compra/{id}":{"get":{"tags":["Órdenes de Compra"],"summary":"Obtener orden de compra por ID","operationId":"obtenerOrdenCompraPorId","parameters":[{"name":"id","in":"path","description":"ID de la orden","required":true,"schema":{"type":"integer","format":"int64"},"example":1}],"responses":{"200":{"description":"OK","content":{"*/*":{"schema":{"$ref":"#/components/schemas/EntityModelOrdenCompraResponseDTO"}}}}}}},"/api/audit-logs":{"get":{"tags":["Auditoría"],"summary":"Listar logs de auditoría de usuarios","operationId":"listarAuditLogs","responses":{"200":{"description":"Lista de registros de auditoría","content":{"*/*":{"schema":{"type":"array","items":{"$ref":"#/components/schemas/AuditLog"}}}}},"401":{"description":"No autenticado"},"403":{"description":"Sin permisos (requiere GERENTE)"}}}}},"components":{"schemas":{"UsuarioRequestDTO":{"type":"object","properties":{"id":{"type":"integer","format":"int64","description":"ID del usuario (solo en actualización)","example":1},"username":{"type":"string","description":"Nombre de usuario único","example":"cliente_nuevo","maxLength":50,"minLength":3},"password":{"type":"string","description":"Contraseña (obligatoria al crear)","example":"cliente123","maxLength":100,"minLength":6},"nombre":{"type":"string","description":"Nombre del usuario","example":"Ana","maxLength":100,"minLength":0},"apellido":{"type":"string","description":"Apellido del usuario","example":"Pérez","maxLength":100,"minLength":0},"email":{"type":"string","description":"Correo electrónico","example":"ana@example.com","maxLength":150,"minLength":0},"direccion":{"type":"string","description":"Dirección del usuario","example":"Calle 123","maxLength":300,"minLength":0},"roleNames":{"type":"array","description":"Roles asignados","example":["CLIENTE"],"items":{"type":"string"}}},"required":["apellido","direccion","email","nombre","username"]},"EntityModelUsuarioResponseDTO":{"type":"object","properties":{"id":{"type":"integer","format":"int64"},"username":{"type":"string"},"nombre":{"type":"string"},"apellido":{"type":"string"},"email":{"type":"string"},"direccion":{"type":"string"},"roles":{"type":"array","items":{"$ref":"#/components/schemas/RolDTO"}},"mfaEnabled":{"type":"boolean"},"_links":{"$ref":"#/components/schemas/Links"}}},"RolDTO":{"type":"object","properties":{"id":{"type":"integer","format":"int64"},"nombre":{"type":"string"}}},"UsuarioResponseDTO":{"type":"object","properties":{"id":{"type":"integer","format":"int64"},"username":{"type":"string"},"nombre":{"type":"string"},"apellido":{"type":"string"},"email":{"type":"string"},"direccion":{"type":"string"},"roles":{"type":"array","items":{"$ref":"#/components/schemas/RolDTO"}},"mfaEnabled":{"type":"boolean"}}},"SucursalRequestDTO":{"type":"object","properties":{"id":{"type":"integer","format":"int64"},"nombre":{"type":"string","maxLength":100,"minLength":0},"direccion":{"type":"string","maxLength":200,"minLength":0},"comuna":{"type":"string","maxLength":100,"minLength":0},"activa":{"type":"boolean"}},"required":["comuna","direccion","nombre"]},"EntityModelSucursalResponseDTO":{"type":"object","properties":{"id":{"type":"integer","format":"int64"},"nombre":{"type":"string"},"direccion":{"type":"string"},"comuna":{"type":"string"},"activa":{"type":"boolean"},"_links":{"$ref":"#/components/schemas/Links"}}},"SucursalResponseDTO":{"type":"object","properties":{"id":{"type":"integer","format":"int64"},"nombre":{"type":"string"},"direccion":{"type":"string"},"comuna":{"type":"string"},"activa":{"type":"boolean"}}},"IdRefDTO":{"type":"object","description":"Referencia por ID a otra entidad","example":{"id":1},"properties":{"id":{"type":"integer","format":"int64","description":"Identificador de la entidad referenciada","example":1}},"required":["id"]},"StockSucursalRequestDTO":{"type":"object","properties":{"id":{"type":"integer","format":"int64"},"producto":{"$ref":"#/components/schemas/IdRefDTO"},"sucursal":{"$ref":"#/components/schemas/IdRefDTO"},"cantidad":{"type":"integer","format":"int32","minimum":0},"stockMinimo":{"type":"integer","format":"int32","minimum":0}},"required":["cantidad","producto","stockMinimo","sucursal"]},"CategoriaResponseDTO":{"type":"object","properties":{"id":{"type":"integer","format":"int64"},"nombre":{"type":"string"}}},"EntityModelStockSucursalResponseDTO":{"type":"object","properties":{"id":{"type":"integer","format":"int64"},"producto":{"$ref":"#/components/schemas/ProductoResponseDTO"},"sucursal":{"$ref":"#/components/schemas/SucursalResponseDTO"},"cantidad":{"type":"integer","format":"int32"},"stockMinimo":{"type":"integer","format":"int32"},"_links":{"$ref":"#/components/schemas/Links"}}},"ProductoResponseDTO":{"type":"object","properties":{"id":{"type":"integer","format":"int64"},"nombre":{"type":"string"},"precio":{"type":"number","format":"double"},"stock":{"type":"integer","format":"int32"},"descripcion":{"type":"string"},"categoria":{"$ref":"#/components/schemas/CategoriaResponseDTO"}}},"PromocionRequestDTO":{"type":"object","properties":{"id":{"type":"integer","format":"int64"},"nombre":{"type":"string","maxLength":100,"minLength":0},"descripcion":{"type":"string","maxLength":2000,"minLength":0},"descuentoPorcentaje":{"type":"number","format":"double","maximum":100.0,"minimum":0.01},"fechaInicio":{"type":"string","format":"date-time"},"fechaFin":{"type":"string","format":"date-time"},"activa":{"type":"boolean"},"producto":{"$ref":"#/components/schemas/IdRefDTO"},"sucursal":{"$ref":"#/components/schemas/IdRefDTO"}},"required":["descuentoPorcentaje","fechaFin","fechaInicio","nombre"]},"EntityModelPromocionResponseDTO":{"type":"object","properties":{"id":{"type":"integer","format":"int64"},"nombre":{"type":"string"},"descripcion":{"type":"string"},"descuentoPorcentaje":{"type":"number","format":"double"},"fechaInicio":{"type":"string","format":"date-time"},"fechaFin":{"type":"string","format":"date-time"},"activa":{"type":"boolean"},"producto":{"$ref":"#/components/schemas/ProductoResponseDTO"},"sucursal":{"$ref":"#/components/schemas/SucursalResponseDTO"},"_links":{"$ref":"#/components/schemas/Links"}}},"PromocionResponseDTO":{"type":"object","properties":{"id":{"type":"integer","format":"int64"},"nombre":{"type":"string"},"descripcion":{"type":"string"},"descuentoPorcentaje":{"type":"number","format":"double"},"fechaInicio":{"type":"string","format":"date-time"},"fechaFin":{"type":"string","format":"date-time"},"activa":{"type":"boolean"},"producto":{"$ref":"#/components/schemas/ProductoResponseDTO"},"sucursal":{"$ref":"#/components/schemas/SucursalResponseDTO"}}},"ProductoRequestDTO":{"type":"object","description":"Datos para crear o actualizar un producto del catálogo","example":{"nombre":"Arroz grano largo 1kg","precio":1890,"stock":10,"descripcion":"Arroz de consumo diario","categoria":{"id":1}},"properties":{"id":{"type":"integer","format":"int64","description":"ID del producto (solo en actualización)","example":1},"nombre":{"type":"string","description":"Nombre comercial del producto","example":"Arroz grano largo 1kg","maxLength":200,"minLength":0},"precio":{"type":"number","format":"double","description":"Precio unitario en pesos chilenos","example":1890},"stock":{"type":"integer","format":"int32","description":"Unidades disponibles en inventario","example":10,"minimum":0},"descripcion":{"type":"string","description":"Descripción del producto","example":"Arroz de consumo diario","maxLength":2000,"minLength":0},"categoria":{"$ref":"#/components/schemas/IdRefDTO","description":"Categoría a la que pertenece el producto"}},"required":["categoria","nombre","precio","stock"]},"EntityModelProductoResponseDTO":{"type":"object","properties":{"id":{"type":"integer","format":"int64"},"nombre":{"type":"string"},"precio":{"type":"number","format":"double"},"stock":{"type":"integer","format":"int32"},"descripcion":{"type":"string"},"categoria":{"$ref":"#/components/schemas/CategoriaResponseDTO"},"_links":{"$ref":"#/components/schemas/Links"}}},"InventarioRequestDTO":{"type":"object","properties":{"id":{"type":"integer","format":"int64","description":"ID del movimiento (solo en actualización)","example":1},"producto":{"$ref":"#/components/schemas/IdRefDTO","description":"Producto asociado al movimiento"},"cantidad":{"type":"integer","format":"int32","description":"Cantidad del movimiento","example":10,"minimum":1},"tipoMovimiento":{"type":"string","description":"Tipo de movimiento: Entrada o Salida","example":"Entrada","maxLength":50,"minLength":0},"fechaMovimiento":{"type":"string","format":"date-time","description":"Fecha del movimiento (opcional, se asigna automáticamente si no se envía)"}},"required":["cantidad","producto","tipoMovimiento"]},"EntityModelInventarioResponseDTO":{"type":"object","properties":{"id":{"type":"integer","format":"int64"},"producto":{"$ref":"#/components/schemas/ProductoResponseDTO"},"cantidad":{"type":"integer","format":"int32"},"tipoMovimiento":{"type":"string"},"fechaMovimiento":{"type":"string","format":"date-time"},"_links":{"$ref":"#/components/schemas/Links"}}},"DetalleVentaRequestDTO":{"type":"object","properties":{"id":{"type":"integer","format":"int64"},"venta":{"$ref":"#/components/schemas/IdRefDTO"},"producto":{"$ref":"#/components/schemas/IdRefDTO"},"cantidad":{"type":"integer","format":"int32","minimum":1},"precio":{"type":"number","format":"double","minimum":0}},"required":["cantidad","precio","producto","venta"]},"DetalleVentaResponseDTO":{"type":"object","properties":{"id":{"type":"integer","format":"int64"},"venta":{"$ref":"#/components/schemas/IdRefDTO"},"producto":{"$ref":"#/components/schemas/ProductoResponseDTO"},"cantidad":{"type":"integer","format":"int32"},"precio":{"type":"number","format":"double"}}},"CategoriaRequestDTO":{"type":"object","properties":{"id":{"type":"integer","format":"int64"},"nombre":{"type":"string","maxLength":100,"minLength":0}},"required":["nombre"]},"EntityModelCategoriaResponseDTO":{"type":"object","properties":{"id":{"type":"integer","format":"int64"},"nombre":{"type":"string"},"_links":{"$ref":"#/components/schemas/Links"}}},"CarritoRequestDTO":{"type":"object","description":"Datos para agregar o modificar un item en el carrito de compras","example":{"usuario":{"id":1},"producto":{"id":1},"cantidad":2},"properties":{"id":{"type":"integer","format":"int64","description":"ID del item en carrito (solo en actualización)","example":1},"usuario":{"$ref":"#/components/schemas/IdRefDTO","description":"Usuario propietario del carrito"},"producto":{"$ref":"#/components/schemas/IdRefDTO","description":"Producto a agregar al carrito"},"cantidad":{"type":"integer","format":"int32","description":"Cantidad de unidades","example":2,"minimum":1}},"required":["cantidad","producto","usuario"]},"EntityModelCarritoResponseDTO":{"type":"object","properties":{"id":{"type":"integer","format":"int64"},"usuario":{"$ref":"#/components/schemas/UsuarioResponseDTO"},"producto":{"$ref":"#/components/schemas/ProductoResponseDTO"},"cantidad":{"type":"integer","format":"int32"},"_links":{"$ref":"#/components/schemas/Links"}}},"VentaRequestDTO":{"type":"object","properties":{"id":{"type":"integer","format":"int64"},"usuario":{"$ref":"#/components/schemas/IdRefDTO"},"fecha":{"type":"string","format":"date-time"}},"required":["usuario"]},"EntityModelVentaResponseDTO":{"type":"object","properties":{"id":{"type":"integer","format":"int64"},"usuario":{"$ref":"#/components/schemas/UsuarioResponseDTO"},"fecha":{"type":"string","format":"date-time"},"total":{"type":"number","format":"double"},"_links":{"$ref":"#/components/schemas/Links"}}},"VentaItemDTO":{"type":"object","properties":{"productoId":{"type":"integer","format":"int64"},"cantidad":{"type":"integer","format":"int32","minimum":1}},"required":["cantidad","productoId"]},"VentaRegistroDTO":{"type":"object","properties":{"usuarioId":{"type":"integer","format":"int64"},"items":{"type":"array","items":{"$ref":"#/components/schemas/VentaItemDTO"},"minItems":1}},"required":["items","usuarioId"]},"PedidoItemDTO":{"type":"object","properties":{"productoId":{"type":"integer","format":"int64"},"cantidad":{"type":"integer","format":"int32","minimum":1}},"required":["cantidad","productoId"]},"PedidoRegistroDTO":{"type":"object","properties":{"usuarioId":{"type":"integer","format":"int64"},"sucursalId":{"type":"integer","format":"int64"},"tipoEntrega":{"type":"string","minLength":1},"direccionEntrega":{"type":"string"},"items":{"type":"array","items":{"$ref":"#/components/schemas/PedidoItemDTO"},"minItems":1}},"required":["items","sucursalId","tipoEntrega","usuarioId"]},"DetallePedidoResponseDTO":{"type":"object","properties":{"id":{"type":"integer","format":"int64"},"producto":{"$ref":"#/components/schemas/ProductoResponseDTO"},"cantidad":{"type":"integer","format":"int32"},"precioUnitario":{"type":"number","format":"double"},"subtotal":{"type":"number","format":"double"}}},"EntityModelPedidoResponseDTO":{"type":"object","properties":{"id":{"type":"integer","format":"int64"},"usuario":{"$ref":"#/components/schemas/UsuarioResponseDTO"},"sucursal":{"$ref":"#/components/schemas/SucursalResponseDTO"},"fecha":{"type":"string","format":"date-time"},"estado":{"type":"string"},"tipoEntrega":{"type":"string"},"direccionEntrega":{"type":"string"},"total":{"type":"number","format":"double"},"detalles":{"type":"array","items":{"$ref":"#/components/schemas/DetallePedidoResponseDTO"}},"_links":{"$ref":"#/components/schemas/Links"}}},"DetalleOrdenCompraResponseDTO":{"type":"object","properties":{"id":{"type":"integer","format":"int64"},"producto":{"$ref":"#/components/schemas/ProductoResponseDTO"},"cantidad":{"type":"integer","format":"int32"},"costoUnitario":{"type":"number","format":"double"}}},"EntityModelOrdenCompraResponseDTO":{"type":"object","properties":{"id":{"type":"integer","format":"int64"},"proveedor":{"type":"string"},"sucursal":{"$ref":"#/components/schemas/SucursalResponseDTO"},"fecha":{"type":"string","format":"date-time"},"estado":{"type":"string"},"detalles":{"type":"array","items":{"$ref":"#/components/schemas/DetalleOrdenCompraResponseDTO"}},"_links":{"$ref":"#/components/schemas/Links"}}},"RegisterRequest":{"type":"object","properties":{"username":{"type":"string","maxLength":50,"minLength":3},"password":{"type":"string","maxLength":100,"minLength":6},"nombre":{"type":"string","maxLength":100,"minLength":0},"apellido":{"type":"string","maxLength":100,"minLength":0},"email":{"type":"string","maxLength":150,"minLength":0},"direccion":{"type":"string","maxLength":300,"minLength":0}},"required":["apellido","direccion","email","nombre","password","username"]},"TokenPairResponse":{"type":"object","properties":{"accessToken":{"type":"string"},"refreshToken":{"type":"string"},"type":{"type":"string"},"expiresIn":{"type":"integer","format":"int64"},"username":{"type":"string"},"roles":{"type":"array","items":{"type":"string"}},"mfaRequired":{"type":"boolean"},"mfaToken":{"type":"string"},"token":{"type":"string"}}},"RefreshTokenRequest":{"type":"object","properties":{"refreshToken":{"type":"string","minLength":1}},"required":["refreshToken"]},"MfaVerifyRequest":{"type":"object","properties":{"mfaToken":{"type":"string","minLength":1},"code":{"type":"string","maxLength":6,"minLength":6}},"required":["code","mfaToken"]},"MfaSetupResponse":{"type":"object","properties":{"secret":{"type":"string"},"qrUri":{"type":"string"}}},"MfaConfirmRequest":{"type":"object","properties":{"code":{"type":"string","maxLength":6,"minLength":6}},"required":["code"]},"MapMessage":{"type":"object","properties":{"message":{"type":"string"}}},"LogoutRequest":{"type":"object","properties":{"refreshToken":{"type":"string","minLength":1}},"required":["refreshToken"]},"LoginRequest":{"type":"object","properties":{"username":{"type":"string","minLength":1},"password":{"type":"string","minLength":1}},"required":["password","username"]},"PedidoEstadoUpdateDTO":{"type":"object","properties":{"estado":{"type":"string","minLength":1}},"required":["estado"]},"PagedResourcesAssemblerVentaResponseDTO":{"type":"object","properties":{"forceFirstAndLastRels":{"type":"boolean","writeOnly":true}}},"PageMetadata":{"type":"object","properties":{"size":{"type":"integer","format":"int64"},"totalElements":{"type":"integer","format":"int64"},"totalPages":{"type":"integer","format":"int64"},"number":{"type":"integer","format":"int64"}}},"PagedModelEntityModelVentaResponseDTO":{"type":"object","properties":{"_embedded":{"type":"object","properties":{"ventaResponseDTOList":{"type":"array","items":{"$ref":"#/components/schemas/EntityModelVentaResponseDTO"}}}},"_links":{"$ref":"#/components/schemas/Links"},"page":{"$ref":"#/components/schemas/PageMetadata"}}},"PagedResourcesAssemblerUsuarioResponseDTO":{"type":"object","properties":{"forceFirstAndLastRels":{"type":"boolean","writeOnly":true}}},"PagedModelEntityModelUsuarioResponseDTO":{"type":"object","properties":{"_embedded":{"type":"object","properties":{"usuarioResponseDTOList":{"type":"array","items":{"$ref":"#/components/schemas/EntityModelUsuarioResponseDTO"}}}},"_links":{"$ref":"#/components/schemas/Links"},"page":{"$ref":"#/components/schemas/PageMetadata"}}},"PagedResourcesAssemblerSucursalResponseDTO":{"type":"object","properties":{"forceFirstAndLastRels":{"type":"boolean","writeOnly":true}}},"PagedModelEntityModelSucursalResponseDTO":{"type":"object","properties":{"_embedded":{"type":"object","properties":{"sucursalResponseDTOList":{"type":"array","items":{"$ref":"#/components/schemas/EntityModelSucursalResponseDTO"}}}},"_links":{"$ref":"#/components/schemas/Links"},"page":{"$ref":"#/components/schemas/PageMetadata"}}},"PagedResourcesAssemblerStockSucursalResponseDTO":{"type":"object","properties":{"forceFirstAndLastRels":{"type":"boolean","writeOnly":true}}},"PagedModelEntityModelStockSucursalResponseDTO":{"type":"object","properties":{"_embedded":{"type":"object","properties":{"stockSucursalResponseDTOList":{"type":"array","items":{"$ref":"#/components/schemas/EntityModelStockSucursalResponseDTO"}}}},"_links":{"$ref":"#/components/schemas/Links"},"page":{"$ref":"#/components/schemas/PageMetadata"}}},"DisponibilidadResponseDTO":{"type":"object","properties":{"productoId":{"type":"integer","format":"int64"},"productoNombre":{"type":"string"},"precio":{"type":"number","format":"double"},"cantidadDisponible":{"type":"integer","format":"int32"},"disponible":{"type":"boolean"}}},"RotacionProductoResponseDTO":{"type":"object","properties":{"productoId":{"type":"integer","format":"int64"},"productoNombre":{"type":"string"},"cantidadVentas":{"type":"integer","format":"int32"},"cantidadPedidos":{"type":"integer","format":"int32"},"totalRotacion":{"type":"integer","format":"int32"}}},"PagedResourcesAssemblerPromocionResponseDTO":{"type":"object","properties":{"forceFirstAndLastRels":{"type":"boolean","writeOnly":true}}},"PagedModelEntityModelPromocionResponseDTO":{"type":"object","properties":{"_embedded":{"type":"object","properties":{"promocionResponseDTOList":{"type":"array","items":{"$ref":"#/components/schemas/EntityModelPromocionResponseDTO"}}}},"_links":{"$ref":"#/components/schemas/Links"},"page":{"$ref":"#/components/schemas/PageMetadata"}}},"PagedResourcesAssemblerProductoResponseDTO":{"type":"object","properties":{"forceFirstAndLastRels":{"type":"boolean","writeOnly":true}}},"PagedResourcesAssemblerPedidoResponseDTO":{"type":"object","properties":{"forceFirstAndLastRels":{"type":"boolean","writeOnly":true}}},"PagedModelEntityModelPedidoResponseDTO":{"type":"object","properties":{"_embedded":{"type":"object","properties":{"pedidoResponseDTOList":{"type":"array","items":{"$ref":"#/components/schemas/EntityModelPedidoResponseDTO"}}}},"_links":{"$ref":"#/components/schemas/Links"},"page":{"$ref":"#/components/schemas/PageMetadata"}}},"PagedResourcesAssemblerOrdenCompraResponseDTO":{"type":"object","properties":{"forceFirstAndLastRels":{"type":"boolean","writeOnly":true}}},"PagedModelEntityModelOrdenCompraResponseDTO":{"type":"object","properties":{"_embedded":{"type":"object","properties":{"ordenCompraResponseDTOList":{"type":"array","items":{"$ref":"#/components/schemas/EntityModelOrdenCompraResponseDTO"}}}},"_links":{"$ref":"#/components/schemas/Links"},"page":{"$ref":"#/components/schemas/PageMetadata"}}},"PagedResourcesAssemblerInventarioResponseDTO":{"type":"object","properties":{"forceFirstAndLastRels":{"type":"boolean","writeOnly":true}}},"PagedModelEntityModelInventarioResponseDTO":{"type":"object","properties":{"_embedded":{"type":"object","properties":{"inventarioResponseDTOList":{"type":"array","items":{"$ref":"#/components/schemas/EntityModelInventarioResponseDTO"}}}},"_links":{"$ref":"#/components/schemas/Links"},"page":{"$ref":"#/components/schemas/PageMetadata"}}},"PagedResourcesAssemblerCategoriaResponseDTO":{"type":"object","properties":{"forceFirstAndLastRels":{"type":"boolean","writeOnly":true}}},"PagedModelEntityModelCategoriaResponseDTO":{"type":"object","properties":{"_embedded":{"type":"object","properties":{"categoriaResponseDTOList":{"type":"array","items":{"$ref":"#/components/schemas/EntityModelCategoriaResponseDTO"}}}},"_links":{"$ref":"#/components/schemas/Links"},"page":{"$ref":"#/components/schemas/PageMetadata"}}},"PagedResourcesAssemblerCarritoResponseDTO":{"type":"object","properties":{"forceFirstAndLastRels":{"type":"boolean","writeOnly":true}}},"PagedModelEntityModelCarritoResponseDTO":{"type":"object","properties":{"_embedded":{"type":"object","properties":{"carritoResponseDTOList":{"type":"array","items":{"$ref":"#/components/schemas/EntityModelCarritoResponseDTO"}}}},"_links":{"$ref":"#/components/schemas/Links"},"page":{"$ref":"#/components/schemas/PageMetadata"}}},"AuditLog":{"type":"object","properties":{"id":{"type":"integer","format":"int64"},"username":{"type":"string"},"action":{"type":"string"},"resource":{"type":"string"},"resourceId":{"type":"integer","format":"int64"},"ipAddress":{"type":"string"},"userAgent":{"type":"string"},"timestamp":{"type":"string","format":"date-time"},"success":{"type":"boolean"}}},"Link":{"type":"object","properties":{"href":{"type":"string"},"hreflang":{"type":"string"},"title":{"type":"string"},"type":{"type":"string"},"deprecation":{"type":"string"},"profile":{"type":"string"},"name":{"type":"string"},"templated":{"type":"boolean"}}},"Links":{"type":"object","additionalProperties":{"$ref":"#/components/schemas/Link"}}},"securitySchemes":{"bearerAuth":{"type":"http","description":"Token JWT obtenido en POST /api/auth/login o /api/auth/register","scheme":"bearer","bearerFormat":"JWT"}}}}